pixellab/__init__.py
pixellab/animate_with_skeleton.py
pixellab/animate_with_text.py
pixellab/client.py
pixellab/estimate_skeleton.py
pixellab/generate_image_bitforge.py
pixellab/generate_image_pixflux.py
pixellab/get_balance.py
pixellab/inpaint.py
pixellab/models/__init__.py
pixellab/models/base64_image.py
pixellab/models/image_size.py
pixellab/models/keypoint.py
pixellab/rotate.py
pixellab/settings.py
pixellab/types.py
pixellab-1.0.5.dist-info/METADATA
pixellab-1.0.5.dist-info/WHEEL
pixellab-1.0.5.dist-info/RECORD
