Metadata-Version: 2.1
Name: pixellab
Version: 1.0.5
Summary: 
Author: PixelLab
Requires-Python: >=3.8,<4.0
Classifier: Programming Language :: Python :: 3
Classifier: Programming Language :: Python :: 3.8
Classifier: Programming Language :: Python :: 3.9
Classifier: Programming Language :: Python :: 3.10
Classifier: Programming Language :: Python :: 3.11
Classifier: Programming Language :: Python :: 3.12
Requires-Dist: eval-type-backport ; python_version < "3.10"
Requires-Dist: pillow
Requires-Dist: pydantic (>=2.0.0,<3.0.0)
Requires-Dist: pydantic-settings (>=2.0.0,<3.0.0)
Requires-Dist: requests (>=2.0.0,<3.0.0)
